[
  {
    "image": "https://m.media-amazon.com/images/W/MEDIAX_792452-T1/images/I/31PykOKnnIL._SY445_SX342_.jpg",
    "type": "biography",
    "movie": "The Case For Trump",
    "director": "Victor Davis Hanson",
    "rating": "7",
    "reviews": "6",
    "bestSelling":"true",
    "id": "1"
  },
  {
    "image": "https://images-na.ssl-images-amazon.com/images/S/compressed.photo.goodreads.com/books/1530963561i/35068465.jpg",
    "type": "drama",
    "movie": "The Last Romantics",
    "director": "Tara Conklin",
    "rating": "8",
    "reviews": "7",
    "bestSelling":"true",
    "id": "2"
  },
  {
    "image": "https://m.media-amazon.com/images/W/MEDIAX_792452-T1/images/I/41-TmRZP71L._SY445_SX342_.jpg",
    "type": "drama",
    "movie": "An Anonymos Girl",
    "director": "Greer Hendricks",
    "rating": "7",
    "reviews": "158",
    "bestSelling":"true",
    "id": "3"
  },
  {
    "image": "https://images-na.ssl-images-amazon.com/images/S/compressed.photo.goodreads.com/books/1562475601l/51072736.jpg",
    "type": "drama",
    "movie": "Peaky Blinders",
    "director": "Caryn Mandabach",
    "rating": "9",
    "reviews": "866",
    "bestSelling":"false",
    "id": "4"
  },
  {
    "image": "https://m.media-amazon.com/images/W/MEDIAX_792452-T1/images/I/31PykOKnnIL._SY445_SX342_.jpg",
    "type": "biography",
    "movie": "The Case For Trump",
    "director": "Victor Davis Hanson",
    "rating": "7",
    "reviews": "6",
    "bestSelling":"true",
    "id": "5"
  },
  {
    "image": "https://images-na.ssl-images-amazon.com/images/S/compressed.photo.goodreads.com/books/1530963561i/35068465.jpg",
    "type": "drama",
    "movie": "The Last Romantics",
    "director": "Tara Conklin",
    "rating": "8",
    "reviews": "7",
    "bestSelling":"true",
    "id": "6"
  },
  {
    "image": "https://m.media-amazon.com/images/W/MEDIAX_792452-T1/images/I/41-TmRZP71L._SY445_SX342_.jpg",
    "type": "drama",
    "movie": "An Anonymos Girl",
    "director": "Greer Hendricks",
    "rating": "7",
    "reviews": "158",
    "bestSelling":"true",
    "id": "7"
  },
  {
    "image": "https://images-na.ssl-images-amazon.com/images/S/compressed.photo.goodreads.com/books/1562475601l/51072736.jpg",
    "type": "drama",
    "movie": "Peaky Blinders",
    "director": "Caryn Mandabach",
    "rating": "9",
    "reviews": "866",
    "bestSelling":"false",
    "id": "8"
  }
]
